py_zkp/__init__.py
py_zkp/groth16/__init__.py
py_zkp/groth16/code_to_r1cs.py
py_zkp/groth16/determinant.py
py_zkp/groth16/poly_utils.py
py_zkp/groth16/proving.py
py_zkp/groth16/qap_creator.py
py_zkp/groth16/qap_creator_lcm.py
py_zkp/groth16/setup.py
py_zkp/groth16/verifying.py
py_zkp/plonk/__init__.py
py_zkp/tokamak_snarks/__init__.py
py_zkp-0.1.0.dist-info/METADATA
py_zkp-0.1.0.dist-info/WHEEL
py_zkp-0.1.0.dist-info/top_level.txt
py_zkp-0.1.0.dist-info/RECORD
