Metadata-Version: 2.1
Name: py-zkp
Version: 0.1.0
Summary: py-zkp: ZKP in python including groth16, plonk, tokamak_snarks
Home-page: https://github.com/tokamak-network/py_zkp
Author: Tokamak Network
Author-email: kevin@tokamak.network
Keywords: zkp
Classifier: Development Status :: 2 - Pre-Alpha
Classifier: Intended Audience :: Developers
Classifier: Natural Language :: English
Classifier: Programming Language :: Python :: 3
Classifier: Programming Language :: Python :: 3.8
Classifier: Programming Language :: Python :: 3.9
Classifier: Programming Language :: Python :: 3.10
Classifier: Programming Language :: Python :: 3.11
Classifier: Programming Language :: Python :: 3.12
Requires-Python: >=3.8, <4
Requires-Dist: py-ecc ==7.0.1
Provides-Extra: dev
Requires-Dist: build >=1.2.2 ; extra == 'dev'
